kicad_parts_placer/__init__.py
kicad_parts_placer/cli.py
kicad_parts_placer/kicad_parts_placer.py
kicad_parts_placer-0.1.4.dist-info/LICENSE
kicad_parts_placer-0.1.4.dist-info/METADATA
kicad_parts_placer-0.1.4.dist-info/WHEEL
kicad_parts_placer-0.1.4.dist-info/entry_points.txt
kicad_parts_placer-0.1.4.dist-info/top_level.txt
kicad_parts_placer-0.1.4.dist-info/RECORD
