Metadata-Version: 2.1
Name: kicad_parts_placer
Version: 0.1.4
Summary: Place components in a kicad file programmatically.
Author-email: Simon Hobbs <simon.hobbs@electrooptical.net>
License: MIT License
Project-URL: github, https://github.com/snhobbs/kicad-parts-placer.git
Keywords: kicad_parts_placer,kicad,python,eda,electronics,pcb,manufacturing
Classifier: Development Status :: 2 - Pre-Alpha
Classifier: Intended Audience :: Developers
Classifier: Natural Language :: English
Classifier: Programming Language :: Python :: 3
Classifier: Programming Language :: Python :: 3.6
Classifier: Programming Language :: Python :: 3.7
Classifier: Programming Language :: Python :: 3.8
Requires-Python: >=3.8
License-File: LICENSE
Requires-Dist: click >=7.0
Requires-Dist: pandas
Requires-Dist: numpy
Requires-Dist: spreadsheet-wrangler >=0.1.3
